hermes_audio_server/__init__.py
hermes_audio_server/about.py
hermes_audio_server/cli.py
hermes_audio_server/exceptions.py
hermes_audio_server/logger.py
hermes_audio_server/mqtt.py
hermes_audio_server/player.py
hermes_audio_server/recorder.py
hermes_audio_server/config/__init__.py
hermes_audio_server/config/mqtt.py
hermes_audio_server/config/vad.py
hermes_audio_server-0.2.0.data/scripts/hermes-audio-player
hermes_audio_server-0.2.0.data/scripts/hermes-audio-recorder
hermes_audio_server-0.2.0.dist-info/LICENSE
hermes_audio_server-0.2.0.dist-info/METADATA
hermes_audio_server-0.2.0.dist-info/WHEEL
hermes_audio_server-0.2.0.dist-info/top_level.txt
hermes_audio_server-0.2.0.dist-info/RECORD
