Metadata-Version: 2.1
Name: hermes-audio-server
Version: 0.2.0
Summary: An open source implementation of the audio server part of the Hermes protocol
Home-page: https://github.com/koenvervloesem/hermes-audio-server
Author: Koen Vervloesem
Author-email: koen@vervloesem.eu
License: MIT License
Project-URL: Documentation, https://github.com/koenvervloesem/hermes-audio-server
Project-URL: Source, https://github.com/koenvervloesem/hermes-audio-server
Project-URL: Tracker, https://github.com/koenvervloesem/hermes-audio-server/issues
Keywords: hermes snips python3 rhasspy audio-player audio-recorder audio-server snips-audio-server hermes-protocol voice voice-control
Platform: UNKNOWN
Classifier: Development Status :: 3 - Alpha
Classifier: Environment :: Console
Classifier: License :: OSI Approved :: MIT License
Classifier: Operating System :: POSIX
Classifier: Programming Language :: Python
Classifier: Programming Language :: Python :: 3 :: Only
Classifier: Programming Language :: Python :: 3.5
Classifier: Programming Language :: Python :: 3.6
Classifier: Programming Language :: Python :: 3.7
Classifier: Programming Language :: Python :: Implementation :: CPython
Classifier: Topic :: Home Automation
Classifier: Topic :: Multimedia :: Sound/Audio :: Capture/Recording
Classifier: Topic :: Multimedia :: Sound/Audio :: Players
Requires-Python: >=3
Requires-Dist: colorlog
Requires-Dist: humanfriendly
Requires-Dist: paho-mqtt
Requires-Dist: plac
Requires-Dist: pyaudio
Requires-Dist: python-daemon
Requires-Dist: webrtcvad
